pyway/__init__.py
pyway/checksum.py
pyway/clean.py
pyway/configfile.py
pyway/errors.py
pyway/exceptions.py
pyway/helpers.py
pyway/import_.py
pyway/info.py
pyway/log.py
pyway/migrate.py
pyway/migration.py
pyway/repair.py
pyway/settings.py
pyway/validate.py
pyway/version.py
pyway/dbms/__init__.py
pyway/dbms/database.py
pyway/dbms/duckdb.py
pyway/dbms/mysql.py
pyway/dbms/postgres.py
pyway/dbms/sqlite.py
pyway/scripts/__init__.py
pyway/scripts/main.py
pyway-0.3.32.dist-info/LICENSE
pyway-0.3.32.dist-info/METADATA
pyway-0.3.32.dist-info/WHEEL
pyway-0.3.32.dist-info/entry_points.txt
pyway-0.3.32.dist-info/top_level.txt
pyway-0.3.32.dist-info/RECORD
