Metadata-Version: 2.1
Name: pyway
Version: 0.3.32
Summary: Pyway is a database versioning and migration tool inspired by Flyway
Author-email: Jason Camp <me@jason.camp>
License: GPL
Project-URL: Homepage, https://github.com/jasondcamp/pyway
Classifier: Development Status :: 4 - Beta
Classifier: License :: OSI Approved :: GNU General Public License v3 (GPLv3)
Classifier: Programming Language :: Python :: 3.9
Classifier: Programming Language :: Python :: 3.10
Classifier: Programming Language :: Python :: 3.11
Classifier: Programming Language :: Python :: 3.12
Requires-Python: >=3.9
License-File: LICENSE
Requires-Dist: tabulate ==0.9.0
Requires-Dist: psycopg2-binary >=2.9.5
Requires-Dist: mysql-connector-python >=9.1.0
Requires-Dist: pyyaml >=6.0.1
Requires-Dist: strip-ansi >=0.1.1
Provides-Extra: tests
Requires-Dist: pytest >=7.2.1 ; extra == 'tests'
Requires-Dist: pytest-env >=0.8.1 ; extra == 'tests'
Requires-Dist: pytest-cov >=4.0.0 ; extra == 'tests'
Requires-Dist: coverage >=7.2.1 ; extra == 'tests'
Requires-Dist: mysqld-integration-test >=0.0.28 ; extra == 'tests'
